{
  "name": "shared_ukgprowfmpeople",
  "id": "/providers/Microsoft.PowerApps/apis/shared_ukgprowfmpeople",
  "type": "/providers/Microsoft.PowerApps/apis",
  "properties": {
    "displayName": "UKG Pro WFM People",
    "iconUri": "https://conn-afd-prod-endpoint-bmc9bqahasf3grgk.b01.azurefd.net/releases/v1.0.1705/1.0.1705.3833/ukgprowfmpeople/icon.png",
    "purpose": "NotSpecified",
    "connectionParameters": {
      "api_key": {
        "type": "securestring",
        "uiDefinition": {
          "displayName": "PRO WFM Vanity URL",
          "description": "The PRO WFM Vanity URL for this api",
          "tooltip": "Provide your PRO WFM Vanity URL",
          "constraints": {
            "tabIndex": 2,
            "clearText": false,
            "required": "true"
          }
        }
      }
    },
    "metadata": {
      "source": "marketplace",
      "brandColor": "#005151",
      "stackOwner": "Ultimate Kronos Group Incorporated",
      "useNewApimVersion": "true",
      "version": {
        "previous": "releases/v1.0.1697\\1.0.1697.3784",
        "current": "releases/v1.0.1705\\1.0.1705.3833"
      }
    },
    "capabilities": [],
    "tier": "Premium",
    "isCustomApi": false,
    "description": "Pulls person Current User Information (Logged In User)",
    "createdTime": "2024-06-13T22:43:22.0917111Z",
    "changedTime": "2025-01-11T02:38:57.2439207Z",
    "publisher": "Dilip Chenani"
  }
}
