{
  "name": "shared_documentaikonfuzio",
  "id": "/providers/Microsoft.PowerApps/apis/shared_documentaikonfuzio",
  "type": "/providers/Microsoft.PowerApps/apis",
  "properties": {
    "displayName": "Document AI Konfuzio",
    "iconUri": "https://connectoricons-prod.azureedge.net/releases/v1.0.1525/1.0.1525.2578/documentaikonfuzio/icon.png",
    "purpose": "NotSpecified",
    "connectionParameters": {
      "username": {
        "type": "securestring",
        "uiDefinition": {
          "displayName": "username",
          "description": "The username for this api",
          "tooltip": "Provide the username",
          "constraints": {
            "tabIndex": 2,
            "clearText": true,
            "required": "true"
          }
        }
      },
      "password": {
        "type": "securestring",
        "uiDefinition": {
          "displayName": "password",
          "description": "The password for this api",
          "tooltip": "Provide the password",
          "constraints": {
            "tabIndex": 3,
            "clearText": false,
            "required": "true"
          }
        }
      }
    },
    "metadata": {
      "source": "marketplace",
      "brandColor": "#44b78b",
      "stackOwner": "Helm & Nagel GmbH",
      "useNewApimVersion": "true",
      "version": {
        "previous": "releases/v1.0.1502\\1.0.1502.2508",
        "current": "releases/v1.0.1525\\1.0.1525.2578"
      }
    },
    "capabilities": [
      "actions"
    ],
    "tier": "Premium",
    "isCustomApi": false,
    "description": "Use the document AI Konfuzio Connector to OCR, extract, and retrieve structured information from PDFs, images, handwriting, and scans. Register on https://app.konfuzio.com for free to OCR PDFs and images from various file types, see https://dev.konfuzio.com/web/api.html#supported-file-types. In addition, you can train your custom Document AI following the Tutorial on https://help.konfuzio.com/tutorials/quickstart/ to extract structured information from documents.",
    "createdTime": "2021-07-30T21:58:40.7311501Z",
    "changedTime": "2021-10-11T18:07:32.6022733Z",
    "publisher": "Helm & Nagel GmbH"
  }
}
