{
  "name": "shared_enadoc",
  "id": "/providers/Microsoft.PowerApps/apis/shared_enadoc",
  "type": "/providers/Microsoft.PowerApps/apis",
  "properties": {
    "displayName": "Enadoc",
    "iconUri": "https://connectoricons-prod.azureedge.net/releases/v1.0.1528/1.0.1528.2589/enadoc/icon.png",
    "purpose": "NotSpecified",
    "connectionParameters": {
      "token": {
        "type": "oauthSetting",
        "oAuthSettings": {
          "identityProvider": "oauth2",
          "clientId": "10272020105136",
          "scopes": [
            "enadoc_ip"
          ],
          "redirectMode": "Global",
          "redirectUrl": "https://global.consent.azure-apim.net/redirect",
          "properties": {
            "IsFirstParty": "False",
            "IsOnbehalfofLoginSupported": false
          },
          "customParameters": {
            "authorizationUrl": {
              "value": "https://auth.enadocapp.com/oauth2/authorize"
            },
            "tokenUrl": {
              "value": "https://enadocapp.com/api/v3/token"
            },
            "refreshUrl": {
              "value": "https://enadocapp.com/api/v3/token"
            }
          }
        }
      }
    },
    "scopes": {
      "will": [],
      "wont": []
    },
    "metadata": {
      "source": "marketplace",
      "brandColor": "#0d93d2",
      "stackOwner": "Enadoc Pte Ltd",
      "useNewApimVersion": "true",
      "version": {
        "previous": "releases/v1.0.1420\\1.0.1420.2245",
        "current": "releases/v1.0.1528\\1.0.1528.2589"
      }
    },
    "capabilities": [
      "actions"
    ],
    "tier": "Premium",
    "isCustomApi": false,
    "description": "Enadoc is an innovative, cloud-based enterprise document imaging system. Enadoc provides solutions for secure and reliable management of documents on the cloud, with capabilities such as archival, search, retrieval and sharing of documents.",
    "createdTime": "2018-09-18T19:35:34.4036947Z",
    "changedTime": "2021-10-14T16:38:03.0035734Z",
    "publisher": "Enadoc Pte Ltd"
  }
}
