{
  "name": "shared_langai",
  "id": "/providers/Microsoft.PowerApps/apis/shared_langai",
  "type": "/providers/Microsoft.PowerApps/apis",
  "properties": {
    "displayName": "Lang.ai",
    "iconUri": "https://connectoricons-prod.azureedge.net/u/shgogna/version-mismatches-special-train/1.0.1670.3520/langai/icon.png",
    "purpose": "NotSpecified",
    "connectionParameters": {
      "api_key": {
        "type": "securestring",
        "uiDefinition": {
          "displayName": "API Key",
          "description": "The API Key for this api",
          "tooltip": "Provide your API Key",
          "constraints": {
            "tabIndex": 2,
            "clearText": false,
            "required": "true"
          }
        }
      },
      "tenant": {
        "type": "string",
        "uiDefinition": {
          "constraints": {
            "required": "true"
          },
          "description": "Specify your tenant name",
          "displayName": "Tenant Name",
          "tooltip": "Provide Your Tenant: (us.app or eu.app or [companyname])"
        }
      }
    },
    "metadata": {
      "source": "marketplace",
      "brandColor": "#3E4EB8",
      "stackOwner": "Lang.ai",
      "useNewApimVersion": "true",
      "version": {
        "previous": "releases/v1.0.1604\\1.0.1604.3062",
        "current": "u/shgogna/version-mismatches-special-train\\1.0.1670.3520"
      }
    },
    "capabilities": [
      "actions"
    ],
    "tier": "Premium",
    "isCustomApi": false,
    "description": "Lang.ai is a SaaS platform that automate time-consuming manual tasks like tagging, prioritization and routing.AI that literally takes minutes to implement as you build your tags combining concepts visually instead of spending months using a traditional AI approach.",
    "createdTime": "2021-07-14T01:21:21.606517Z",
    "changedTime": "2023-12-08T00:58:06.1225383Z",
    "publisher": "Lang.ai"
  }
}
