{
  "name": "shared_imanagedatamarts",
  "id": "/providers/Microsoft.PowerApps/apis/shared_imanagedatamarts",
  "type": "/providers/Microsoft.PowerApps/apis",
  "properties": {
    "displayName": "iManage Data Marts",
    "iconUri": "https://conn-afd-prod-endpoint-bmc9bqahasf3grgk.b01.azurefd.net/v1.0.1759/1.0.1759.4267/imanagedatamarts/icon.png",
    "purpose": "NotSpecified",
    "connectionParameters": {
      "token": {
        "type": "oauthSetting",
        "oAuthSettings": {
          "identityProvider": "oauth2",
          "clientId": "3e1f0a96-4d30-41ad-b0fa-934de5eae0c3",
          "scopes": [
            "user"
          ],
          "redirectMode": "GlobalPerConnector",
          "redirectUrl": "https://global.consent.azure-apim.net/redirect/imanagedatamarts",
          "properties": {
            "IsFirstParty": "False",
            "IsOnbehalfofLoginSupported": false
          },
          "customParameters": {
            "AuthorizationUrl": {
              "value": "https://cloudimanage.com/auth/oauth2/authorize"
            },
            "TokenUrl": {
              "value": "https://cloudimanage.com/auth/oauth2/token"
            },
            "RefreshUrl": {
              "value": "https://cloudimanage.com/auth/oauth2/token"
            }
          }
        },
        "uiDefinition": {
          "displayName": "OAuth Connection",
          "description": "OAuth Connection",
          "constraints": {
            "required": "true",
            "hidden": "false"
          }
        }
      }
    },
    "metadata": {
      "source": "marketplace",
      "brandColor": "#1302e7",
      "stackOwner": "iManage Power Platform Connector",
      "useNewApimVersion": "true",
      "version": {
        "previous": "",
        "current": "v1.0.1759\\1.0.1759.4267"
      }
    },
    "capabilities": [
      "actions"
    ],
    "tier": "Premium",
    "isCustomApi": false,
    "description": "The iManage Data Marts connector pushes metadata updates for matters, clients, and other Work product entities into the iManage platform via a structured data mart interface.",
    "createdTime": "2025-07-02T06:09:02.0451448Z",
    "changedTime": "2025-07-02T06:09:11.0036784Z",
    "publisher": "iManage Power Platform Connector"
  }
}
