{
  "name": "shared_parserr",
  "id": "/providers/Microsoft.PowerApps/apis/shared_parserr",
  "type": "/providers/Microsoft.PowerApps/apis",
  "properties": {
    "displayName": "Parserr",
    "iconUri": "https://connectoricons-prod.azureedge.net/releases/v1.0.1538/1.0.1538.2619/parserr/icon.png",
    "purpose": "NotSpecified",
    "connectionParameters": {
      "username": {
        "type": "string",
        "uiDefinition": {
          "displayName": "Username",
          "description": "Parserr username.",
          "tooltip": "Provide your username",
          "constraints": {
            "required": "true"
          }
        }
      },
      "password": {
        "type": "securestring",
        "uiDefinition": {
          "displayName": "Password",
          "description": "Parserr password.",
          "tooltip": "Provide your password",
          "constraints": {
            "required": "true"
          }
        }
      }
    },
    "scopes": {
      "will": [],
      "wont": []
    },
    "metadata": {
      "source": "marketplace",
      "brandColor": "#f7bb2e",
      "useNewApimVersion": "true",
      "version": {
        "previous": "releases/v1.0.1380\\1.0.1380.2095",
        "current": "releases/v1.0.1538\\1.0.1538.2619"
      }
    },
    "capabilities": [
      "actions",
      "triggers"
    ],
    "tier": "Standard",
    "isCustomApi": false,
    "description": "Parserr allows you extract data from recurring incoming emails and Excel, CSV and PDF attachments",
    "createdTime": "2018-09-06T17:45:45.848542Z",
    "changedTime": "2021-11-18T19:07:30.3406603Z",
    "publisher": "Parserr LLC"
  }
}
