{
  "name": "shared_redquesmartinvoiceca",
  "id": "/providers/Microsoft.PowerApps/apis/shared_redquesmartinvoiceca",
  "type": "/providers/Microsoft.PowerApps/apis",
  "properties": {
    "displayName": "Redque",
    "iconUri": "https://connectoricons-prod.azureedge.net/releases/v1.0.1631/1.0.1631.3267/redquesmartinvoiceca/icon.png",
    "purpose": "NotSpecified",
    "connectionParameters": {
      "token": {
        "type": "oauthSetting",
        "oAuthSettings": {
          "identityProvider": "oauth2",
          "clientId": "pwra_redque",
          "scopes": [
            "v1.public",
            "offline_access"
          ],
          "redirectMode": "Global",
          "redirectUrl": "https://global.consent.azure-apim.net/redirect",
          "properties": {
            "IsFirstParty": "False",
            "IsOnbehalfofLoginSupported": false
          },
          "customParameters": {
            "authorizationUrl": {
              "value": "https://demoidentity.redque.com/connect/authorize"
            },
            "tokenUrl": {
              "value": "https://demoidentity.redque.com/connect/token"
            },
            "refreshUrl": {
              "value": "https://demoidentity.redque.com/connect/token"
            }
          }
        },
        "uiDefinition": {
          "displayName": "Log in with RedQue Account",
          "description": "Log in with RedQue Account",
          "tooltip": "Log in with RedQue Account",
          "constraints": {
            "required": "true"
          }
        }
      }
    },
    "metadata": {
      "source": "marketplace",
      "brandColor": "#000000",
      "stackOwner": "Redque s.r.o.",
      "useNewApimVersion": "true",
      "version": {
        "previous": "",
        "current": "releases/v1.0.1631\\1.0.1631.3267"
      }
    },
    "capabilities": [
      "actions"
    ],
    "tier": "Premium",
    "isCustomApi": false,
    "description": "Accessing and managing the Redque system.",
    "createdTime": "2023-04-14T18:16:53.8817065Z",
    "changedTime": "2023-04-14T18:16:53.8817065Z",
    "publisher": "Redque s.r.o."
  }
}
